well_profile/__init__.py
well_profile/create_trajectory.py
well_profile/equations.py
well_profile/generator.py
well_profile/load_trajectory.py
well_profile/plot.py
well_profile/well.py
well_profile-0.8.1.dist-info/LICENSE.md
well_profile-0.8.1.dist-info/METADATA
well_profile-0.8.1.dist-info/WHEEL
well_profile-0.8.1.dist-info/top_level.txt
well_profile-0.8.1.dist-info/RECORD
