Metadata-Version: 2.1
Name: well-profile
Version: 0.8.1
Summary: Well Profile Builder
Home-page: https://github.com/pro-well-plan/well_profile
Author: Pro Well Plan AS
Author-email: juan@prowellplan.com
License: LGPL v3
Keywords: drilling,well,trajectory,engineering
Classifier: Programming Language :: Python :: 3
Classifier: License :: OSI Approved :: GNU Lesser General Public License v3 (LGPLv3)
Classifier: Natural Language :: English
Classifier: Topic :: Scientific/Engineering
Classifier: Topic :: Software Development
Classifier: Topic :: Software Development :: Libraries
Classifier: Topic :: Utilities
License-File: LICENSE.md
Requires-Dist: numpy
Requires-Dist: pandas
Requires-Dist: openpyxl
Requires-Dist: plotly
